CHANGELOG.txt
LICENSE.txt
MANIFEST.in
README.txt
main.py
setup.py
AoZhangCalculator/__init__.py
AoZhangCalculator.egg-info/PKG-INFO
AoZhangCalculator.egg-info/SOURCES.txt
AoZhangCalculator.egg-info/dependency_links.txt
AoZhangCalculator.egg-info/top_level.txt
venv/bin/activate_this.py
venv/bin/rst2html.py
venv/bin/rst2html4.py
venv/bin/rst2html5.py
venv/bin/rst2latex.py
venv/bin/rst2man.py
venv/bin/rst2odt.py
venv/bin/rst2odt_prepstyles.py
venv/bin/rst2pseudoxml.py
venv/bin/rst2s5.py
venv/bin/rst2xetex.py
venv/bin/rst2xml.py
venv/bin/rstpep2html.py
venv/lib/python3.9/site-packages/_virtualenv.py
venv/lib/python3.9/site-packages/six.py
venv/lib/python3.9/site-packages/zipp.py
venv/lib/python3.9/site-packages/Pygments-2.12.0.dist-info/entry_points.txt
venv/lib/python3.9/site-packages/Pygments-2.12.0.dist-info/top_level.txt
venv/lib/python3.9/site-packages/_distutils_hack/__init__.py
venv/lib/python3.9/site-packages/_distutils_hack/override.py
venv/lib/python3.9/site-packages/bleach/__init__.py
venv/lib/python3.9/site-packages/bleach/callbacks.py
venv/lib/python3.9/site-packages/bleach/css_sanitizer.py
venv/lib/python3.9/site-packages/bleach/html5lib_shim.py
venv/lib/python3.9/site-packages/bleach/linkifier.py
venv/lib/python3.9/site-packages/bleach/parse_shim.py
venv/lib/python3.9/site-packages/bleach/sanitizer.py
venv/lib/python3.9/site-packages/bleach-5.0.1.dist-info/top_level.txt
venv/lib/python3.9/site-packages/bleach/_vendor/__init__.py
venv/lib/python3.9/site-packages/bleach/_vendor/parse.py
venv/lib/python3.9/site-packages/bleach/_vendor/vendor.txt
venv/lib/python3.9/site-packages/bleach/_vendor/html5lib/__init__.py
venv/lib/python3.9/site-packages/bleach/_vendor/html5lib/_ihatexml.py
venv/lib/python3.9/site-packages/bleach/_vendor/html5lib/_inputstream.py
venv/lib/python3.9/site-packages/bleach/_vendor/html5lib/_tokenizer.py
venv/lib/python3.9/site-packages/bleach/_vendor/html5lib/_utils.py
venv/lib/python3.9/site-packages/bleach/_vendor/html5lib/constants.py
venv/lib/python3.9/site-packages/bleach/_vendor/html5lib/html5parser.py
venv/lib/python3.9/site-packages/bleach/_vendor/html5lib/serializer.py
venv/lib/python3.9/site-packages/bleach/_vendor/html5lib-1.1.dist-info/top_level.txt
venv/lib/python3.9/site-packages/bleach/_vendor/html5lib/_trie/__init__.py
venv/lib/python3.9/site-packages/bleach/_vendor/html5lib/_trie/_base.py
venv/lib/python3.9/site-packages/bleach/_vendor/html5lib/_trie/py.py
venv/lib/python3.9/site-packages/certifi-2022.6.15.dist-info/top_level.txt
venv/lib/python3.9/site-packages/charset_normalizer-2.1.0.dist-info/entry_points.txt
venv/lib/python3.9/site-packages/charset_normalizer-2.1.0.dist-info/top_level.txt
venv/lib/python3.9/site-packages/commonmark-0.9.1.dist-info/entry_points.txt
venv/lib/python3.9/site-packages/commonmark-0.9.1.dist-info/top_level.txt
venv/lib/python3.9/site-packages/docutils-0.19.dist-info/COPYING.txt
venv/lib/python3.9/site-packages/docutils-0.19.dist-info/entry_points.txt
venv/lib/python3.9/site-packages/docutils-0.19.dist-info/top_level.txt
venv/lib/python3.9/site-packages/idna-3.3.dist-info/top_level.txt
venv/lib/python3.9/site-packages/importlib_metadata-4.12.0.dist-info/top_level.txt
venv/lib/python3.9/site-packages/keyring-23.6.0.dist-info/entry_points.txt
venv/lib/python3.9/site-packages/keyring-23.6.0.dist-info/top_level.txt
venv/lib/python3.9/site-packages/pip-21.3.1.dist-info/LICENSE.txt
venv/lib/python3.9/site-packages/pip-21.3.1.dist-info/entry_points.txt
venv/lib/python3.9/site-packages/pip-21.3.1.dist-info/top_level.txt
venv/lib/python3.9/site-packages/pkginfo-1.8.3.dist-info/LICENSE.txt
venv/lib/python3.9/site-packages/pkginfo-1.8.3.dist-info/entry_points.txt
venv/lib/python3.9/site-packages/pkginfo-1.8.3.dist-info/top_level.txt
venv/lib/python3.9/site-packages/readme_renderer-35.0.dist-info/top_level.txt
venv/lib/python3.9/site-packages/requests-2.28.1.dist-info/top_level.txt
venv/lib/python3.9/site-packages/requests_toolbelt-0.9.1.dist-info/top_level.txt
venv/lib/python3.9/site-packages/rfc3986-2.0.0.dist-info/top_level.txt
venv/lib/python3.9/site-packages/setuptools-60.2.0.dist-info/entry_points.txt
venv/lib/python3.9/site-packages/setuptools-60.2.0.dist-info/top_level.txt
venv/lib/python3.9/site-packages/six-1.16.0.dist-info/top_level.txt
venv/lib/python3.9/site-packages/twine-4.0.1.dist-info/entry_points.txt
venv/lib/python3.9/site-packages/twine-4.0.1.dist-info/top_level.txt
venv/lib/python3.9/site-packages/urllib3-1.26.10.dist-info/LICENSE.txt
venv/lib/python3.9/site-packages/urllib3-1.26.10.dist-info/top_level.txt
venv/lib/python3.9/site-packages/webencodings-0.5.1.dist-info/top_level.txt
venv/lib/python3.9/site-packages/wheel-0.37.1.dist-info/LICENSE.txt
venv/lib/python3.9/site-packages/wheel-0.37.1.dist-info/entry_points.txt
venv/lib/python3.9/site-packages/wheel-0.37.1.dist-info/top_level.txt
venv/lib/python3.9/site-packages/zipp-3.8.1.dist-info/top_level.txt